<testdata>
	<Framework>

		<Signin_TestData_0>

			<NormalEmail>cktest@gmail.com</NormalEmail>
			<Password>ppounds</Password>

		</Signin_TestData_0>

		<Signin_TestDataForFB_1>

			<FacebookEmail>dev@pouringpounds.com</FacebookEmail>
			<Password>fblogindev@1S</Password>

		</Signin_TestDataForFB_1>

		<Signin_TestDataForAdmin_2>

			<UserName>dev</UserName>
			<Password>ppstaging@2C</Password>

		</Signin_TestDataForAdmin_2>

		<Store_TestData_3>

			<StoreName>Amazon India</StoreName>
			<StoreDescription></StoreDescription>
			<StoreUrl>https://www.amazon.in</StoreUrl>

		</Store_TestData_3>

	</Framework>
</testdata>